setup.py
pymongo_dbref/__init__.py
pymongo_dbref.egg-info/PKG-INFO
pymongo_dbref.egg-info/SOURCES.txt
pymongo_dbref.egg-info/dependency_links.txt
pymongo_dbref.egg-info/requires.txt
pymongo_dbref.egg-info/top_level.txt