Metadata-Version: 1.0
Name: pymongo-dbref
Version: 0.0.1
Summary: auto mongodb dbref
Home-page: https://github.com/windprog/pymongo-dbref
Author: windpro
Author-email: windprog@gmai.com
License: UNKNOWN
Platform: UNKNOWN
